LICENSE
MANIFEST.in
README.md
setup.cfg
setup.py
rdb_comp_tap_hubspot/__init__.py
rdb_comp_tap_hubspot/rdb_comp_tap_hubspot.py
rdb_comp_tap_hubspot.egg-info/PKG-INFO
rdb_comp_tap_hubspot.egg-info/SOURCES.txt
rdb_comp_tap_hubspot.egg-info/dependency_links.txt
rdb_comp_tap_hubspot.egg-info/entry_points.txt
rdb_comp_tap_hubspot.egg-info/requires.txt
rdb_comp_tap_hubspot.egg-info/top_level.txt
rdb_comp_tap_hubspot/schemas/campaigns.json
rdb_comp_tap_hubspot/schemas/companies.json
rdb_comp_tap_hubspot/schemas/contact_lists.json
rdb_comp_tap_hubspot/schemas/contacts.json
rdb_comp_tap_hubspot/schemas/contacts_by_company.json
rdb_comp_tap_hubspot/schemas/deal_pipelines.json
rdb_comp_tap_hubspot/schemas/deals.json
rdb_comp_tap_hubspot/schemas/email_events.json
rdb_comp_tap_hubspot/schemas/engagements.json
rdb_comp_tap_hubspot/schemas/forms.json
rdb_comp_tap_hubspot/schemas/owners.json
rdb_comp_tap_hubspot/schemas/subscription_changes.json
rdb_comp_tap_hubspot/schemas/workflows.json