Metadata-Version: 1.1
Name: rdb-comp-tap-hubspot
Version: 1.0.1
Summary: Singer.io tap for extracting data from the HubSpot API that generates a schema that is compatible with a relational database target for each stream. 
Home-page: http://singer.io
Author: Stitch
Author-email: UNKNOWN
License: UNKNOWN
Platform: UNKNOWN
Classifier: Programming Language :: Python :: 3 :: Only
